cloud_finder/__init__.py
cloud_finder-1.6.1.dist-info/licenses/LICENSE
cloud_finder-1.6.1.dist-info/METADATA
cloud_finder-1.6.1.dist-info/WHEEL
cloud_finder-1.6.1.dist-info/top_level.txt
cloud_finder-1.6.1.dist-info/RECORD
