Metadata-Version: 2.4
Name: cloud-finder
Version: 1.6.1
Summary: Keyword cloud and topic hotspot detection in documents. Find where keywords concentrate to detect topic relevance.
License: MIT
Project-URL: Homepage, https://github.com/LifeAITools/cloud-finder
Project-URL: Issues, https://github.com/LifeAITools/cloud-finder/issues
Keywords: keyword,cloud,topic,detection,hotspot,nlp,text,relevance,clustering,density
Classifier: Development Status :: 5 - Production/Stable
Classifier: Intended Audience :: Developers
Classifier: License :: OSI Approved :: MIT License
Classifier: Operating System :: OS Independent
Classifier: Programming Language :: Python :: 3
Classifier: Programming Language :: Python :: 3.8
Classifier: Programming Language :: Python :: 3.9
Classifier: Programming Language :: Python :: 3.10
Classifier: Programming Language :: Python :: 3.11
Classifier: Programming Language :: Python :: 3.12
Classifier: Topic :: Text Processing :: Indexing
Classifier: Topic :: Text Processing :: Linguistic
Requires-Python: >=3.8
License-File: LICENSE
Requires-Dist: vibe-finder>=1.5.0
Dynamic: license-file
